{
  "insert-template": [
    {
      "modifiers": [
        "Alt",
        "Mod"
      ],
      "key": "T"
    }
  ],
  "templater-obsidian:000 Templates/Concept Template.md": [
    {
      "modifiers": [
        "Alt",
        "Mod"
      ],
      "key": "C"
    }
  ],
  "editor:toggle-source": [
    {
      "modifiers": [
        "Alt",
        "Mod"
      ],
      "key": "S"
    }
  ],
  "editor:swap-line-down": [
    {
      "modifiers": [
        "Alt",
        "Mod"
      ],
      "key": "J"
    }
  ],
  "editor:swap-line-up": [
    {
      "modifiers": [
        "Alt",
        "Mod"
      ],
      "key": "K"
    }
  ],
  "templater-obsidian:replace-in-file-templater": [
    {
      "modifiers": [
        "Alt",
        "Mod"
      ],
      "key": "D"
    }
  ],
  "obsidian-latex-suite:latex-suite-enable-all-features": [
    {
      "modifiers": [
        "Alt",
        "Mod"
      ],
      "key": "Z"
    }
  ],
  "obsidian-latex-suite:latex-suite-disable-all-features": [
    {
      "modifiers": [
        "Alt",
        "Mod"
      ],
      "key": "X"
    }
  ],
  "templater-obsidian:000 Templates/Video Template.md": [
    {
      "modifiers": [
        "Alt",
        "Mod"
      ],
      "key": "V"
    }
  ],
  "editor:insert-table": [
    {
      "modifiers": [
        "Alt",
        "Mod"
      ],
      "key": "A"
    }
  ],
  "templater-obsidian:000 Templates/Article template.md": [
    {
      "modifiers": [
        "Alt",
        "Mod"
      ],
      "key": "Q"
    }
  ],
  "obsidian-linter:lint-file": [],
  "templater-obsidian:000 Templates/Cyber security template.md": [
    {
      "modifiers": [
        "Alt",
        "Mod"
      ],
      "key": "B"
    }
  ],
  "obsidian-latex-suite:latex-suite-box-equation": [
    {
      "modifiers": [
        "Alt",
        "Shift"
      ],
      "key": "B"
    }
  ],
  "daily-notes": [
    {
      "modifiers": [
        "Mod",
        "Shift"
      ],
      "key": "D"
    }
  ],
  "templater-obsidian:000 Templates/Lecture Template.md": [
    {
      "modifiers": [
        "Mod",
        "Shift"
      ],
      "key": "L"
    }
  ],
  "obsidian-read-it-later:save-clipboard-to-notice": [
    {
      "modifiers": [
        "Alt",
        "Mod"
      ],
      "key": "N"
    }
  ],
  "templater-obsidian:090 System/000 Templates/Homework Template.md": [
    {
      "modifiers": [
        "Alt",
        "Mod"
      ],
      "key": "H"
    }
  ],
  "obsidian-excalidraw-plugin:excalidraw-insert-transclusion": [
    {
      "modifiers": [
        "Alt",
        "Mod",
        "Shift"
      ],
      "key": "D"
    }
  ],
  "obsidian-excalidraw-plugin:excalidraw-autocreate-and-embed-new-tab": [
    {
      "modifiers": [
        "Alt",
        "Mod",
        "Shift"
      ],
      "key": "C"
    }
  ]
}